_mbag.cpython-313-aarch64-linux-gnu.so
mbag/__init__.py
mbag/compatibility_utils.py
mbag/agents/__init__.py
mbag/agents/action_distributions.py
mbag/agents/hardcoded_agents.py
mbag/agents/heuristic_agents.py
mbag/agents/human_agent.py
mbag/agents/mbag_agent.py
mbag/c_extensions/_mbagmodule.c
mbag/c_extensions/action_distributions.c
mbag/c_extensions/blocks.c
mbag/c_extensions/mcts.c
mbag/environment/__init__.py
mbag/environment/actions.py
mbag/environment/blocks.py
mbag/environment/config.py
mbag/environment/mbag_env.py
mbag/environment/schedule.py
mbag/environment/state.py
mbag/environment/types.py
mbag/environment/goals/__init__.py
mbag/environment/goals/craftassist.py
mbag/environment/goals/demonstrations.py
mbag/environment/goals/filters.py
mbag/environment/goals/goal_generator.py
mbag/environment/goals/goal_transform.py
mbag/environment/goals/grabcraft.py
mbag/environment/goals/simple.py
mbag/environment/goals/transforms.py
mbag/environment/malmo/__init__.py
mbag/environment/malmo/ai_actions.py
mbag/environment/malmo/malmo_client.py
mbag/environment/malmo/malmo_interface.py
mbag/environment/malmo/malmo_state.py
mbag/environment/malmo/thread_utils.py
mbag/evaluation/__init__.py
mbag/evaluation/episode.py
mbag/evaluation/evaluator.py
mbag/evaluation/metrics.py
mbag/rllib/__init__.py
mbag/rllib/agents.py
mbag/rllib/bc.py
mbag/rllib/callbacks.py
mbag/rllib/data_augmentation.py
mbag/rllib/gail.py
mbag/rllib/human_data.py
mbag/rllib/kl_regularization.py
mbag/rllib/mixture_model.py
mbag/rllib/os_utils.py
mbag/rllib/policies.py
mbag/rllib/ppo.py
mbag/rllib/rllib_env.py
mbag/rllib/sacred_utils.py
mbag/rllib/torch_action_distributions.py
mbag/rllib/torch_models.py
mbag/rllib/training_utils.py
mbag/rllib/alpha_zero/__init__.py
mbag/rllib/alpha_zero/alpha_zero.py
mbag/rllib/alpha_zero/alpha_zero_policy.py
mbag/rllib/alpha_zero/mcts.py
mbag/rllib/alpha_zero/planning.py
mbag/rllib/alpha_zero/replay_buffer.py
mbag_gensyn-0.0.6.dist-info/METADATA
mbag_gensyn-0.0.6.dist-info/WHEEL
mbag_gensyn-0.0.6.dist-info/top_level.txt
mbag_gensyn-0.0.6.dist-info/RECORD
