Metadata-Version: 2.4
Name: mbag-gensyn
Version: 0.0.6
Summary: Code for the ICML 2025 paper "AssistanceZero: Scalably Solving Assistance Games".
Author-email: Cassidy Laidlaw <cassidy_laidlaw@cs.berkeley.edu>
Project-URL: Homepage, https://cassidylaidlaw.github.io/minecraft-building-assistance-game/
Classifier: Development Status :: 3 - Alpha
Classifier: Intended Audience :: Science/Research
Classifier: Topic :: Scientific/Engineering :: Artificial Intelligence
Classifier: License :: OSI Approved :: MIT License
Classifier: Programming Language :: Python :: 3
Classifier: Programming Language :: Python :: 3.10
Classifier: Programming Language :: Python :: 3.11
Requires-Python: <4.0,>=3.10
Requires-Dist: numpy==1.26.4
Requires-Dist: connected-components-3d==3.12.3
Requires-Dist: types-PyYAML==5.4.3
Requires-Dist: gymnasium>=0.28
Requires-Dist: scikit-image>=0.21
Requires-Dist: tqdm
Provides-Extra: dev
Requires-Dist: flake8; extra == "dev"
Requires-Dist: black; extra == "dev"
Requires-Dist: mypy; extra == "dev"
Requires-Dist: pytest; extra == "dev"
Requires-Dist: pytest-timeout; extra == "dev"
Requires-Dist: memray<1.12; extra == "dev"
Requires-Dist: pytest-memray; extra == "dev"
Requires-Dist: pep8-naming; extra == "dev"
Requires-Dist: isort; extra == "dev"
Requires-Dist: types-psutil; extra == "dev"
Provides-Extra: rllib
Requires-Dist: ray[rllib]==2.7.1; extra == "rllib"
Requires-Dist: torch>=1.8; extra == "rllib"
Requires-Dist: sacred==0.8.4; extra == "rllib"
Requires-Dist: einops>=0.3.0; extra == "rllib"
Requires-Dist: braceexpand>=0.1.7; extra == "rllib"
Provides-Extra: malmo
Requires-Dist: mbag-malmo>=0.38.0; extra == "malmo"
